adminbot
