Metadata-Version: 1.1
Name: adminbot
Version: 0.1.1
Summary: A Telegram bot to admin your server
Home-page: https://github.com/Dih5/adminbot
Author: Dih5
Author-email: guillehg@gmail.com
License: MIT
Keywords: system administration
Platform: UNKNOWN
Classifier: Development Status :: 3 - Alpha
Classifier: Intended Audience :: System Administrators
Classifier: Topic :: System :: Monitoring
Classifier: License :: OSI Approved :: MIT License
Classifier: Programming Language :: Python :: 2
Classifier: Programming Language :: Python :: 2.6
Classifier: Programming Language :: Python :: 2.7
Classifier: Programming Language :: Python :: 3
Classifier: Programming Language :: Python :: 3.3
Classifier: Programming Language :: Python :: 3.4
Classifier: Programming Language :: Python :: 3.5
